banana_prompts/__init__.py
banana_prompts-1767513.690.29.dist-info/licenses/LICENSE
banana_prompts-1767513.690.29.dist-info/METADATA
banana_prompts-1767513.690.29.dist-info/WHEEL
banana_prompts-1767513.690.29.dist-info/top_level.txt
banana_prompts-1767513.690.29.dist-info/RECORD
