Metadata-Version: 2.4
Name: banana-prompts
Version: 1767513.690.29
Summary: High-quality integration for https://bananaproai.com/banana-prompts/
Home-page: https://bananaproai.com/banana-prompts/
Author: SuperMaker
Classifier: Programming Language :: Python :: 3
Classifier: License :: OSI Approved :: MIT License
Requires-Python: >=3.6
License-File: LICENSE
Dynamic: author
Dynamic: classifier
Dynamic: description
Dynamic: description-content-type
Dynamic: home-page
Dynamic: license-file
Dynamic: requires-python
Dynamic: summary
